rndqts/__init__.py
rndqts/data/__init__.py
rndqts/data/lazydataframe.py
rndqts/data/ticker.py
rndqts/quotes/__init__.py
rndqts/quotes/real.py
rndqts/quotes/realistic.py
rndqts/quotes/synthetic.py
rndqts/quotes/abs/__init__.py
rndqts/quotes/abs/quotes.py
rndqts-0.2105.28.dist-info/LICENSE
rndqts-0.2105.28.dist-info/METADATA
rndqts-0.2105.28.dist-info/WHEEL
rndqts-0.2105.28.dist-info/top_level.txt
rndqts-0.2105.28.dist-info/RECORD
