Metadata-Version: 2.1
Name: rndqts
Version: 0.2105.28
Summary: Random stock quotes generator based on real data distribution
Home-page: https://github.com/davips/rndqts
Author: Davi Pereira-Santos
Author-email: dpsabc@gmail.com
License: GPL3
Download-URL: https://github.com/davips/rndqts/releases
Platform: UNKNOWN
Classifier: Intended Audience :: Science/Research
Classifier: License :: OSI Approved :: GNU General Public License v3 (GPLv3)
Classifier: Natural Language :: English
Classifier: Programming Language :: Python
Classifier: Topic :: Scientific/Engineering
Classifier: Programming Language :: Python :: 3.7
Requires-Dist: yfinance
Requires-Dist: matplotlib
Requires-Dist: plotly
Requires-Dist: numpy
Requires-Dist: garoupa
